indoxMiner/__init__.py
indoxMiner/classification/__init__.py
indoxMiner/classification/altclip_classifier.py
indoxMiner/classification/base_classifier.py
indoxMiner/classification/bioclip_classifier.py
indoxMiner/classification/biomedclip_classifier.py
indoxMiner/classification/metaclip_classifier.py
indoxMiner/classification/mobileclip_classifier.py
indoxMiner/classification/remoteclip_classifier.py
indoxMiner/classification/sigclip_classifier.py
indoxMiner/classification/vit_classifier.py
indoxMiner/detection/__init__.py
indoxMiner/detection/detector.py
indoxMiner/detection/models/__init__.py
indoxMiner/detection/models/YOLO/__init__.py
indoxMiner/detection/models/YOLO/YOLOX/__init__.py
indoxMiner/detection/models/YOLO/YOLOX/yolox.py
indoxMiner/detection/models/YOLO/YOLOv10/__init__.py
indoxMiner/detection/models/YOLO/YOLOv10/yolov10.py
indoxMiner/detection/models/YOLO/YOLOv11/__init__.py
indoxMiner/detection/models/YOLO/YOLOv11/yolov11.py
indoxMiner/detection/models/YOLO/YOLOv5/__init__.py
indoxMiner/detection/models/YOLO/YOLOv5/yolov5.py
indoxMiner/detection/models/YOLO/YOLOv6/__init__.py
indoxMiner/detection/models/YOLO/YOLOv6/yolov6.py
indoxMiner/detection/models/YOLO/YOLOv7/__init__.py
indoxMiner/detection/models/YOLO/YOLOv7/yolov7.py
indoxMiner/detection/models/YOLO/YOLOv8/__init__.py
indoxMiner/detection/models/YOLO/YOLOv8/yolov8.py
indoxMiner/detection/models/detectron2/__init__.py
indoxMiner/detection/models/detectron2/detectron2.py
indoxMiner/detection/models/detr/__init__.py
indoxMiner/detection/models/detr/detr.py
indoxMiner/detection/models/detr_clip/__init__.py
indoxMiner/detection/models/detr_clip/detr_clip.py
indoxMiner/detection/models/groundedsam2/__init__.py
indoxMiner/detection/models/groundedsam2/groundedsam2.py
indoxMiner/detection/models/groundedsam2florence2/__init__.py
indoxMiner/detection/models/groundedsam2florence2/groundedsam2florence2.py
indoxMiner/detection/models/groundingdino/__init__.py
indoxMiner-0.1.5.dist-info/LICENSE
indoxMiner-0.1.5.dist-info/METADATA
indoxMiner-0.1.5.dist-info/WHEEL
indoxMiner-0.1.5.dist-info/top_level.txt
indoxMiner-0.1.5.dist-info/RECORD
