Metadata-Version: 2.2
Name: indoxMiner
Version: 0.1.5
Summary: Indox Data Extraction
Home-page: https://github.com/osllmai/inDox/libs/indoxMiner
Author: nerdstudio
Author-email: ashkan@nematifamilyfundation.onmicrosoft.com
License: AGPL-3.0
Keywords: document-processing,information-extraction,llm,openai,pdf,text-processing,natural-language-processing
Classifier: Development Status :: 3 - Alpha
Classifier: Intended Audience :: Developers
Classifier: Topic :: Software Development :: Build Tools
Classifier: License :: OSI Approved :: GNU Affero General Public License v3 or later (AGPLv3+)
Classifier: Programming Language :: Python :: 3.9
Classifier: Programming Language :: Python :: 3.10
Classifier: Programming Language :: Python :: 3.11
Classifier: Programming Language :: Python :: 3.12
Requires-Python: >=3.9
License-File: LICENSE
Requires-Dist: latex2markdown
Requires-Dist: loguru
Requires-Dist: pandas~=2.2.2
Requires-Dist: setuptools
Requires-Dist: unstructured~=0.16.4
Requires-Dist: matplotlib
Requires-Dist: numpy
Requires-Dist: utils~=1.0.2
Requires-Dist: requests~=2.32.3
Requires-Dist: unstructured-inference
Requires-Dist: unstructured.pytesseract
Requires-Dist: tesseract
Requires-Dist: pdfminer.six
Requires-Dist: nltk
Requires-Dist: pi_heif
Requires-Dist: opencv_contrib_python
Requires-Dist: opencv_python
Requires-Dist: opencv_python_headless
Requires-Dist: Pillow
Requires-Dist: protobuf
Requires-Dist: Requests
Requires-Dist: supervision
Requires-Dist: torch
Requires-Dist: transformers
Requires-Dist: ultralytics
Dynamic: author
Dynamic: author-email
Dynamic: classifier
Dynamic: description
Dynamic: description-content-type
Dynamic: home-page
Dynamic: keywords
Dynamic: license
Dynamic: requires-dist
Dynamic: requires-python
Dynamic: summary
